{
  "online": {
    "HS_app_id": "250811WWbCJ7W3",
    "TopOn_app_id": "h1gml2aalmqp01",
    "TopOn_app_key": "b1b44444ff8e3638c963fd14133a642d",
    "appkey": "2823737",
    "channel": [
      {
        "AppOpenUnitId": "",
        "BannerUnitId": "ca-app-pub-3803436775068007/3264009812",
        "HS_AppOpenUnitId": "250811LnA3bZBq",
        "HS_BannerUnitId": "250811OXj9rlah",
        "HS_InterstitialUnitId": "250811arWHdYjn",
        "HS_NativeUnitId": "250811wKw6FIvM",
        "HS_RewardInterstitialUnitId": "",
        "HS_RewardUnitId": "250811VgsoHgbM",
        "InterstitialUnitId": "ca-app-pub-3803436775068007/1407152601",
        "NativeUnitId": "ca-app-pub-3803436775068007/9367186069",
        "RewardInterstitialUnitId": "",
        "RewardUnitId": "ca-app-pub-3803436775068007/1299341393",
        "TopOn_AppOpenUnitId": "",
        "TopOn_BannerUnitId": "n1gml2abmv6ror",
        "TopOn_InterstitialUnitId": "n1gml2abmla5p0",
        "TopOn_NativeUnitId": "n1gml2abm1pe7b",
        "TopOn_RewardInterstitialUnitId": "",
        "TopOn_RewardUnitId": "n1gml2abmbgqk2",
        "name": "aha"
      },
      {
        "AppOpenUnitId": "",
        "BannerUnitId": "",
        "HS_AppOpenUnitId": "",
        "HS_BannerUnitId": "",
        "HS_InterstitialUnitId": "",
        "HS_NativeUnitId": "",
        "HS_RewardInterstitialUnitId": "",
        "HS_RewardUnitId": "",
        "InterstitialUnitId": "",
        "NativeUnitId": "",
        "RewardInterstitialUnitId": "",
        "RewardUnitId": "",
        "TopOn_AppOpenUnitId": "",
        "TopOn_BannerUnitId": "",
        "TopOn_InterstitialUnitId": "",
        "TopOn_NativeUnitId": "",
        "TopOn_RewardInterstitialUnitId": "",
        "TopOn_RewardUnitId": "",
        "name": "palm"
      },
      {
        "AppOpenUnitId": "",
        "BannerUnitId": "",
        "HS_AppOpenUnitId": "",
        "HS_BannerUnitId": "",
        "HS_InterstitialUnitId": "",
        "HS_NativeUnitId": "",
        "HS_RewardInterstitialUnitId": "",
        "HS_RewardUnitId": "",
        "InterstitialUnitId": "",
        "NativeUnitId": "",
        "RewardInterstitialUnitId": "",
        "RewardUnitId": "",
        "TopOn_AppOpenUnitId": "",
        "TopOn_BannerUnitId": "",
        "TopOn_InterstitialUnitId": "",
        "TopOn_NativeUnitId": "",
        "TopOn_RewardInterstitialUnitId": "",
        "TopOn_RewardUnitId": "",
        "name": "gp"
      }
    ],
    "google_app_id": "ca-app-pub-3803436775068007~4956365430",
    "tpush_appid": "",
    "tpush_appkey": ""
  },
  "test": {
    "AppOpenUnitId": "ca-app-pub-3940256099942544/9257395921",
    "BannerUnitId": "ca-app-pub-3940256099942544/6300978111",
    "HS_AppOpenUnitId": "250811LnA3bZBq",
    "HS_BannerUnitId": "250811OXj9rlah",
    "HS_InterstitialUnitId": "250811arWHdYjn",
    "HS_NativeUnitId": "250811wKw6FIvM",
    "HS_RewardInterstitialUnitId": "",
    "HS_RewardUnitId": "250811VgsoHgbM",
    "HS_app_id": "250811WWbCJ7W3",
    "InterstitialUnitId": "ca-app-pub-3940256099942544/1033173712",
    "NativeUnitId": "ca-app-pub-3940256099942544/2247696110",
    "RewardInterstitialUnitId": "ca-app-pub-3940256099942544/5354046379",
    "RewardUnitId": "ca-app-pub-3940256099942544/5224354917",
    "TopOn_AppOpenUnitId": "b62b028dcba917",
    "TopOn_BannerUnitId": "b62b03bca998e3",
    "TopOn_InterstitialUnitId": "b62b03b9a8bff9",
    "TopOn_NativeUnitId": "b62b03e2b6c205",
    "TopOn_RewardInterstitialUnitId": "",
    "TopOn_RewardUnitId": "b62b03da735701",
    "TopOn_app_id": "a62b013be01931",
    "TopOn_app_key": "c3d0d2a9a9d451b07e62b509659f7c97",
    "appkey": "2823737",
    "google_app_id": "ca-app-pub-3803436775068007~4956365430",
    "tpush_appid": "",
    "tpush_appkey": ""
  }
}